{
  "config": {
    "branch": "master",
    "cname": "lucent.blog",
    "domain": "http://lucent.blog",
    "email": "975023381@qq.com",
    "platform": "github",
    "privateKey": "",
    "repository": "blog",
    "token": "1a1d4f62e613cfda9db08a00daca881cb5ce769e",
    "username": "xhmily"
  },
  "comment": {
    "commentPlatform": "gitalk",
    "disqusSetting": {
      "api": "",
      "apikey": "",
      "shortname": ""
    },
    "gitalkSetting": {
      "clientId": " f4967b7d0ab0356d6adf",
      "clientSecret": "62264a86a26d73075043a3e31b1669a59faed152",
      "owner": "xhmily",
      "repository": "gitalk-commnet"
    },
    "showComment": false
  }
}